LICENSE
MANIFEST.in
README.md
requirements.txt
setup.py
blocks_cli/__init__.py
blocks_cli/api.py
blocks_cli/builds.py
blocks_cli/bundles.py
blocks_cli/console.py
blocks_cli/fs.py
blocks_cli/package.py
blocks_cli/registration.py
blocks_cli/commands/__base__.py
blocks_cli/commands/__init__.py
blocks_cli/commands/configure.py
blocks_cli/commands/create.py
blocks_cli/commands/init.py
blocks_cli/commands/push.py
blocks_cli/commands/test.py
blocks_cli/config/__init__.py
blocks_cli/config/auth.py
blocks_cli/config/config.py