Metadata-Version: 2.1
Name: blocks-cli
Version: 0.1.40
Summary: CLI tool for Blocks, a platform for writing custom AI-enabled codebase automations in Python. Leverage a full codebase-aware API. Automatically trigger automations from Github, Slack, and other providers.
Home-page: https://github.com/BlocksOrg/sdk
Author: BlocksOrg
Author-email: dev@blocksorg.com
License: AGPL
Classifier: Development Status :: 3 - Alpha
Classifier: Intended Audience :: Developers
Classifier: License :: OSI Approved :: GNU Affero General Public License v3
Classifier: Programming Language :: Python
Classifier: Programming Language :: Python :: 3
Classifier: Programming Language :: Python :: 3.8
Classifier: Programming Language :: Python :: 3.9
Classifier: Programming Language :: Python :: 3.10
Classifier: Programming Language :: Python :: 3.11
Classifier: Operating System :: OS Independent
Classifier: Topic :: Software Development :: Libraries
Classifier: Topic :: Software Development :: Build Tools
Classifier: Topic :: Software Development :: Bug Tracking
Classifier: Topic :: Software Development :: Debuggers
Classifier: Topic :: Software Development :: Code Generators
Classifier: Topic :: Software Development :: Version Control :: Git
Classifier: Topic :: Communications :: Chat
Classifier: Topic :: Scientific/Engineering :: Artificial Intelligence
Requires-Python: >=3.9
License-File: LICENSE
